streambot/__init__.py
streambot-1.1.9.dist-info/METADATA
streambot-1.1.9.dist-info/WHEEL
streambot-1.1.9.dist-info/RECORD
