Metadata-Version: 2.1
Name: streambot
Version: 1.1.9
Summary: An OpenAI ChatGPT wrapper to simplify streaming of token responses to give the writing effect.
Home-page: https://github.com/dr00-eth/StreamBot
License: MIT
Keywords: chatgpt,stream,openai
Author: dr00
Author-email: andrewmeyer23@gmail.com
Requires-Python: >=3.10.0,<4
Classifier: License :: OSI Approved :: MIT License
Classifier: Programming Language :: Python :: 3
Classifier: Programming Language :: Python :: 3.10
Classifier: Programming Language :: Python :: 3.11
Requires-Dist: requests (>=2.28.2,<3.0.0)
Requires-Dist: sseclient-py (>=1.7.2,<2.0.0)
Project-URL: Repository, https://github.com/dr00-eth/StreamBot
